[
  {
    "date": "2025-12-01",
    "scheduledTime": "09:00",
    "theme": "December Countdown",
    "videoIdea": "Create a festive calendar reveal for December promotions.",
    "hashtags": ["#HelloDecember", "#KapeSiglo", "#HolidayCountdown", "#PaskongPampamilya"],
    "description": "Kick off the holiday season with excitement and anticipation.",
    "videoUrl": "/videos/december/01.mp4",
    "label": "December Countdown",
    "caption": "🎄 The most wonderful time of the year starts now! What are you most excited for this December?"
  },
  {
    "date": "2025-12-02",
    "scheduledTime": "10:30",
    "theme": "Gift Guide",
    "videoIdea": "Showcase coffee-themed gift ideas under different budgets.",
    "hashtags": ["#CoffeeGifts", "#HolidayGuide", "#KapeSiglo", "#PamaskongHandog"],
    "description": "Help customers find the perfect presents for coffee lovers.",
    "videoUrl": "/videos/december/02.mp4",
    "label": "Gift Guide",
    "caption": "☕ The gift of good coffee lasts all year round. Here are our top picks!"
  },
  {
    "date": "2025-12-03",
    "scheduledTime": "08:45",
    "theme": "Midweek Warmth",
    "videoIdea": "Slow-motion shots of steaming holiday drinks.",
    "hashtags": ["#WinterWarmth", "#HolidaySips", "#KapeSiglo", "#MainitNaPasko"],
    "description": "Highlight the cozy side of the season.",
    "videoUrl": "/videos/december/03.mp4",
    "label": "Midweek Warmth",
    "caption": "Cold weather calls for warm hearts—and warmer cups."
  },
  {
    "date": "2025-12-04",
    "scheduledTime": "14:20",
    "theme": "Barista's Holiday Pick",
    "videoIdea": "Staff share their favorite seasonal drink.",
    "hashtags": ["#BaristaChoice", "#HolidayMenu", "#KapeSiglo", "#PaboritongPasko"],
    "description": "Build excitement for your holiday specials.",
    "videoUrl": "/videos/december/04.mp4",
    "label": "Barista's Holiday Pick",
    "caption": "Our team's must-try drinks this season—which will you taste first?"
  },
  {
    "date": "2025-12-05",
    "scheduledTime": "11:15",
    "theme": "Festive Setup",
    "videoIdea": "Time-lapse of decorating the café for Christmas.",
    "hashtags": ["#CafeChristmas", "#PaskoNa", "#KapeSiglo", "#PaskongPinoys"],
    "description": "Share your holiday transformation.",
    "videoUrl": "/videos/december/05.mp4",
    "label": "Festive Setup",
    "caption": "Deck the halls with boughs of... coffee beans? ✨ Our café is holiday-ready!"
  },
  {
    "date": "2025-12-06",
    "scheduledTime": "13:00",
    "theme": "Christmas Playlist",
    "videoIdea": "Share your holiday café soundtrack with cozy b-roll.",
    "hashtags": ["#HolidayVibes", "#ChristmasTunes", "#KapeSiglo", "#PaskoSoundtrack"],
    "description": "Combine auditory and visual holiday cheer.",
    "videoUrl": "/videos/december/06.mp4",
    "label": "Christmas Playlist",
    "caption": "Sip, savor, and sing along—your coffee break just got merrier."
  },
  {
    "date": "2025-12-07",
    "scheduledTime": "10:00",
    "theme": "Lantern Sunday",
    "videoIdea": "Feature local parol makers with coffee pairings.",
    "hashtags": ["#ParolMaking", "#PaskongPinoy", "#KapeSiglo", "#SundayVibes"],
    "description": "Celebrate Filipino Christmas traditions.",
    "videoUrl": "/videos/december/07.mp4",
    "label": "Lantern Sunday",
    "caption": "Light, hope, and holiday brews—the perfect December Sunday."
  },
  {
    "date": "2025-12-08",
    "scheduledTime": "08:30",
    "theme": "Feast of the Immaculate Conception",
    "videoIdea": "Peaceful morning shots with a spiritual reflection.",
    "hashtags": ["#December8", "#FeastDay", "#KapeSiglo", "#FaithAndCoffee"],
    "description": "Honor this important religious holiday.",
    "videoUrl": "/videos/december/08.mp4",
    "label": "Feast Day Reflection",
    "caption": "A quiet moment of gratitude on this special day. May your coffee and spirit be warm."
  },
  {
    "date": "2025-12-09",
    "scheduledTime": "15:45",
    "theme": "Holiday Meetup",
    "videoIdea": "Promote your upcoming Christmas customer event.",
    "hashtags": ["#CoffeeMeetup", "#PaskoParty", "#KapeSiglo", "#CommunityCheers"],
    "description": "Build anticipation for your holiday gathering.",
    "videoUrl": "/videos/december/09.mp4",
    "label": "Holiday Meetup",
    "caption": "Mark your calendars—our annual holiday coffee social is coming!"
  },
  {
    "date": "2025-12-10",
    "scheduledTime": "12:30",
    "theme": "Human Rights Day",
    "videoIdea": "Share how your café supports fair trade coffee farmers.",
    "hashtags": ["#HumanRightsDay", "#FairTradeCoffee", "#KapeSiglo", "#EthicalSips"],
    "description": "Align with this important global observance.",
    "videoUrl": "/videos/december/10.mp4",
    "label": "Human Rights Day",
    "caption": "Good coffee starts with good practices. Today we honor those who make our brew possible."
  },
  {
    "date": "2025-12-11",
    "scheduledTime": "09:20",
    "theme": "Christmas Meme",
    "videoIdea": "Holiday-themed coffee humor with trending audio.",
    "hashtags": ["#ChristmasMeme", "#CoffeeHumor", "#KapeSiglo", "#PaskoLaughs"],
    "description": "Lighten up the holiday stress with laughter.",
    "videoUrl": "/videos/december/11.mp4",
    "label": "Christmas Meme",
    "caption": "When you're on your fifth holiday coffee of the day... no regrets!"
  },
  {
    "date": "2025-12-12",
    "scheduledTime": "16:10",
    "theme": "Gingerbread Latte",
    "videoIdea": "Show the making of your signature holiday drink.",
    "hashtags": ["#HolidaySpecial", "#GingerbreadLatte", "#KapeSiglo", "#PaskoFlavors"],
    "description": "Highlight your seasonal menu star.",
    "videoUrl": "/videos/december/12.mp4",
    "label": "Gingerbread Latte",
    "caption": "The taste of Christmas in every sip—our gingerbread latte is back!"
  },
  {
    "date": "2025-12-13",
    "scheduledTime": "14:00",
    "theme": "Holiday Study Session",
    "videoIdea": "Show students enjoying coffee during finals week.",
    "hashtags": ["#StudyMode", "#PaskoBreak", "#KapeSiglo", "#CoffeeFocus"],
    "description": "Support students during stressful exam season.",
    "videoUrl": "/videos/december/13.mp4",
    "label": "Holiday Study Session",
    "caption": "Fuel for finals—we've got your back (and your brain) this exam season."
  },
  {
    "date": "2025-12-14",
    "scheduledTime": "11:30",
    "theme": "Simbang Gabi Prep",
    "videoIdea": "Show early morning coffee service for church-goers.",
    "hashtags": ["#SimbangGabi", "#DawnTradition", "#KapeSiglo", "#PaskongPinoy"],
    "description": "Celebrate this Filipino Christmas tradition.",
    "videoUrl": "/videos/december/14.mp4",
    "label": "Simbang Gabi Prep",
    "caption": "Early mornings call for strong brews. We're open extra early for Simbang Gabi!"
  },
  {
    "date": "2025-12-15",
    "scheduledTime": "10:15",
    "theme": "Holiday Cards",
    "videoIdea": "Show your team signing Christmas cards for regulars.",
    "hashtags": ["#HolidayGreetings", "#CoffeeCommunity", "#KapeSiglo", "#PaskoSpirit"],
    "description": "Show appreciation for your loyal customers.",
    "videoUrl": "/videos/december/15.mp4",
    "label": "Holiday Cards",
    "caption": "Writing warm wishes to those who make our café feel like home."
  },
  {
    "date": "2025-12-16",
    "scheduledTime": "13:45",
    "theme": "Christmas DIY",
    "videoIdea": "Create coffee-themed ornaments or gifts.",
    "hashtags": ["#CoffeeCrafts", "#DIYChristmas", "#KapeSiglo", "#PaskoProjects"],
    "description": "Inspire creative holiday projects.",
    "videoUrl": "/videos/december/16.mp4",
    "label": "Christmas DIY",
    "caption": "Turn your coffee habit into holiday decor—here's how!"
  },
  {
    "date": "2025-12-17",
    "scheduledTime": "09:10",
    "theme": "Midweek Cheer",
    "videoIdea": "Baristas sharing holiday wishes between orders.",
    "hashtags": ["#HolidayCheer", "#MidweekJoy", "#KapeSiglo", "#PaskoVibes"],
    "description": "Spread holiday spirit during the busy week.",
    "videoUrl": "/videos/december/17.mp4",
    "label": "Midweek Cheer",
    "caption": "Because even Wednesdays deserve holiday magic."
  },
  {
    "date": "2025-12-18",
    "scheduledTime": "15:30",
    "theme": "Ube Latte Feature",
    "videoIdea": "Showcase your Filipino-inspired holiday drink.",
    "hashtags": ["#UbeLatte", "#PinoyChristmas", "#KapeSiglo", "#PaskoFlavor"],
    "description": "Highlight your unique local offering.",
    "videoUrl": "/videos/december/18.mp4",
    "label": "Ube Latte Feature",
    "caption": "Purple holiday happiness in a cup—our ube latte is a festive must-try!"
  },
  {
    "date": "2025-12-19",
    "scheduledTime": "12:00",
    "theme": "Squad Christmas Celebration",
    "videoIdea": "Show friend groups enjoying holiday drinks together with festive decorations in the background",
    "hashtags": ["#PaskoParaSaSquad", "#KapeSiglo", "#6daysBeforeChristmas"],
    "description": "Celebrate the joy of friendship this Christmas season with our special squad packages",
    "videoUrl": "/videos/december/19.mp4",
    "label": "Squad Christmas Special",
    "caption": "🎄The Best Gift is Spending time together☕\n\nIpaparamdam namin ang timplang Pasko sa inyong squad! Halina't dumaan sa Kape Siglo at para magsaya, magtawanan, at higit sa lahat, Uminom ng masarap na kape habang nilalasap ang simoy ng Kapaskuhan —dahil ang Pasko ay mas masaya kapag magkakasama! ✨",
    "canvaLink": "https://www.canva.com/design/DAGuWB5pDzs/PtzTHrKGhmMm_g0wP6HgQA/view?utm_content=DAGuWB5pDzs&utm_campaign=designshare&utm_medium=link&utm_source=publishsharelink&mode=preview",
    "imageUrl": "/images/pubmats/dec19.png"
  },
  {
    "date": "2025-12-20",
    "scheduledTime": "17:00",
    "theme": "Holiday Schedule Announcement",
    "videoIdea": "Create an animated graphic showing holiday operating hours with festive coffee visuals",
    "hashtags": ["#KapeSiglo", "#HolidaySchedule", "#PaskongPinoy", "#SupportLocal", "#KapengMayKwento"],
    "description": "Inform customers about our special holiday operating hours with a cheerful visual announcement",
    "videoUrl": "/videos/december/20.mp4",
    "label": "Holiday Schedule",
    "caption": "🎄 KAPE SIGLO HOLIDAY SCHEDULE ☕\n\n📌 CLOSED:\n• December 24–25 (Christmas Break)\n• January 1 (New Year's Day)\n\n📌 OPEN HOURS:\n✅ Dec 26–27: 10:00 AM – 11:00 PM\n✅ Dec 28–30: 3:00 PM – 11:00 PM\n✅ Dec 31: 1:00 PM – 9:00 PM\n✅ Jan 2: 3:00 PM – 11:00 PM\n\nLasapain ang Pasko kasama ang pamilya at isang tasa ng paboritong kape. 🎄☕",
    "canvaLink": "https://www.canva.com/design/DAGuPgk_bEA/nxrgDR1NshRXlO0gDJ3Sow/view?utm_content=DAGuPgk_bEA&utm_campaign=designshare&utm_medium=link&utm_source=publishsharelink&mode=preview",
    "imageUrl": "/images/pubmats/dec20.png"
  },
  {
    "date": "2025-12-21",
    "scheduledTime": "10:45",
    "theme": "Festive Lights Celebration",
    "videoIdea": "Showcase the café's Christmas lights display with customers enjoying warm drinks",
    "hashtags": ["#MaliwanagNaPasko", "#PaskongMakulay", "#KapeSiglo"],
    "description": "Celebrate the brightest nights of the year with our special holiday ambiance and drinks",
    "videoUrl": "/videos/december/21.mp4",
    "label": "Festive Lights Celebration",
    "caption": "✨🎄 Ilaw ng Pasko sa Kape Siglo 🎄✨\n\nSama sama tayong magdiwang sa ilalim ng kumukutikutitap na ilaw at Damahin ang masarap na simoy ng paskuhan sa bawat tsaa ng Kape\n\nGawin makulay ang pasko kasama ng Kape Siglo simula sa maliliwag na ngiti at masarap na kase💡❤️",
    "canvaLink": "https://www.canva.com/design/DAGuV5ohdVI/88MzOP9VLLw2FLNPIELghA/view?utm_content=DAGuV5ohdVI&utm_campaign=designshare&utm_medium=link&utm_source=publishsharelink&mode=preview",
    "imageUrl": "/images/pubmats/dec21.png"
  },
  {
    "date": "2025-12-22",
    "scheduledTime": "14:20",
    "theme": "Barkada Holiday Special",
    "videoIdea": "Show groups of three friends enjoying holiday drinks together with festive ambiance",
    "hashtags": ["#PaskongTrioSaCafe", "#TatluhanAngSaya", "#KapeAtKwentuhan"],
    "description": "Celebrate friendship trios with our special holiday drink packages for groups",
    "videoUrl": "/videos/december/04.mp4",
    "imageUrl": "/images/pubmats/dec22.png",
    "label": "Barkada Holiday Package",
    "caption": "🎄☕ Tatluhan ang Saya: Paskong Trio para lang sa inyo! 🎅👯‍♂️👯\n\nPangtrio ba ang hanap nyo? Tumambay kasama ang iyong barkada, kapatid, o tropang tatluhan at damhin ang masayang Pasko over kape at kwentuhan!\n\nDahil walang makakatalo sa Trio na nakpapakita ng perfect balance katulad ng Kape at Panghimagas sa Kape Siglo",
    "canvaLink": "https://www.canva.com/design/DAGuV0C9NQo/Cg_ucrDGNjzhz1p_1i2pQg/view?utm_content=DAGuV0C9NQo&utm_campaign=designshare&utm_medium=link&utm_source=publishsharelink&mode=preview"
  },
  {
    "date": "2025-12-23",
    "scheduledTime": "14:15",
    "theme": "Noche Buena Pairing",
    "videoIdea": "Suggest coffee drinks to accompany holiday feasts.",
    "hashtags": ["#BisperasNgPasko", "#PaskongMayAntlers", "#ReindeerVibes"],
    "description": "Help plan perfect holiday meals.",
    "videoUrl": "/videos/december/23.mp4",
    "imageUrl": "/images/pubmats/dec23.png",
    "label": "Noche Buena Pairing",
    "caption": "🎄✨ Bisperas ng Pasko ☕🎅\nDamhin ang diwa ng Pasko kasama ang kape Siglo ngayong Disyembre 23! Bago ang noche buena, Tumigil ka muna para maramdaman ang init ng kape at lamig ng simoy ng Pasko. Dahil kahit si Rudolph, humihinto muna para magkape. 😉",
    "canvaLink": "https://www.canva.com/design/DAGuVwW0t14/1jDVSv_bFpHvXgYq6hC9Jw/view?utm_content=DAGuVwW0t14&utm_campaign=designshare&utm_medium=link&utm_source=publishsharelink&mode=preview"
  },
  {
    "date": "2025-12-24",
    "scheduledTime": "09:30",
    "theme": "Christmas Eve",
    "videoIdea": "Quiet morning moments before holiday chaos.",
    "hashtags": ["#ChristmasEve", "#PaskongPasko", "#KapeSiglo", "#PeacefulMorning"],
    "description": "Capture the calm before the celebration.",
    "videoUrl": "/videos/december/24.mp4",
    "label": "Christmas Eve",
    "caption": "One last quiet cup before the holiday magic begins. Merry Christmas Eve!"
  },
    {
    "date": "2025-12-25",
    "scheduledTime": "07:00",
    "theme": "Christmas Day Coffee Celebration",
    "videoIdea": "Show the café team in Christmas attire serving special holiday drinks with festive cheer",
    "hashtags": ["#PaskoSaCafe", "#KapeSiglo", "#ChristmasDayCoffee"],
    "description": "Share the warmth of Christmas through our special holiday coffee offerings",
    "videoUrl": "/videos/december/25.mp4",
    "label": "Christmas Day Special",
    "caption": "🎄☕ Paskong masarap basta may regalong kapeng matatanggap🎁✨\n\nSama-sama tayong magdiwang sa pamamagitan ng masasarap na kape na punong-puno ng pagmamahalan. Dahil ang Pasko para samin ay pasko para sa pagsasama, kwentuhan, at kape na mula sa puso. ☕🌟\n\nMerry Christmas Mula sa Kape Siglo!",
    "imageUrl": "/images/pubmats/dec25.png"
  },
  {
    "date": "2025-12-26",
    "scheduledTime": "12:30",
    "theme": "Boxing Day",
    "videoIdea": "Show your post-Christmas special offers.",
    "hashtags": ["#BoxingDay", "#AfterChristmas", "#KapeSiglo", "#PaskoSale"],
    "description": "Highlight deals for post-holiday shoppers.",
    "videoUrl": "/videos/december/26.mp4",
    "label": "Boxing Day",
    "caption": "The perfect time to treat yourself after all that holiday giving!"
  },
  {
    "date": "2025-12-27",
    "scheduledTime": "11:00",
    "theme": "Year-End Reflections",
    "videoIdea": "Customers share favorite 2025 café memories.",
    "hashtags": ["#YearInReview", "#Memories2025", "#KapeSiglo", "#YearEndCheers"],
    "description": "Celebrate your community's shared experiences.",
    "videoUrl": "/videos/december/27.mp4",
    "label": "Year-End Reflections",
    "caption": "So many memories made over coffee this year—which was your favorite?"
  },
  {
    "date": "2025-12-28",
    "scheduledTime": "15:20",
    "theme": "Sunday Reset",
    "videoIdea": "Calm moments between Christmas and New Year's.",
    "hashtags": ["#YearEndVibes", "#SundayReset", "#KapeSiglo", "#PahingaMuna"],
    "description": "Encourage rest during the busy season.",
    "videoUrl": "/videos/december/28.mp4",
    "label": "Sunday Reset",
    "caption": "The perfect pause between holidays—come recharge with us."
  },
  {
    "date": "2025-12-29",
    "scheduledTime": "10:10",
    "theme": "New Year's Prep",
    "videoIdea": "Show your café preparing for New Year's Eve.",
    "hashtags": ["#NewYearsEve", "#CountdownPrep", "#KapeSiglo", "#BagongTaon"],
    "description": "Build excitement for your NYE offerings.",
    "videoUrl": "/videos/december/29.mp4",
    "label": "New Year's Prep",
    "caption": "Getting ready to toast to new beginnings—are you joining us?"
  },
  {
    "date": "2025-12-30",
    "scheduledTime": "13:50",
    "theme": "Patriotic Coffee Tribute",
    "videoIdea": "Create a respectful tribute video featuring Rizal-inspired coffee art and historical snippets",
    "hashtags": ["#KapeAtKasaysayan", "#ArawNiRizal", "#KapengMakabayan"],
    "description": "Honor Dr. José Rizal's legacy through a special coffee tribute and historical reflection",
    "videoUrl": "/videos/december/30.mp4",
    "label": "Rizal Day Tribute",
    "caption": "☕ Kape't Paggunita, Rizal Day sa aming Café 📖✨\n\nSabay nating alalahanin ang kabayanihan ni Dr. José Rizal. At magsilbing paalala ang araw na ito na ang bawat tagumpay ay nagsisimula sa maliliit na pagkilos at pagmamahal sa bayan. Dahil Katulad Ni José, Madaling magpursigi basta may kapeng katabi",
    "imageUrl": "/images/pubmats/dec30.png"
  },
  {
    "date": "2025-12-31",
    "scheduledTime": "16:00",
    "theme": "New Year's Eve",
    "videoIdea": "Countdown to midnight with coffee toasts.",
    "hashtags": ["#NewYearsEve", "#CountdownTo2026", "#KapeSiglo", "#CheersToNewBeginnings"],
    "description": "Celebrate the year's end with your community.",
    "videoUrl": "/videos/december/31.mp4",
    "label": "New Year's Eve",
    "caption": "Raising our cups to 2025—see you next year! 🎉☕"
  }
]